bullsandcows.py
bullsandcows-1.4.dist-info/LICENSE.txt
bullsandcows-1.4.dist-info/METADATA
bullsandcows-1.4.dist-info/WHEEL
bullsandcows-1.4.dist-info/top_level.txt
bullsandcows-1.4.dist-info/RECORD
