Metadata-Version: 2.1
Name: bullsandcows
Version: 1.4
Summary: Bulls and Cows in Python.
Home-page: https://github.com/ryancflam/Bulls-and-Cows
Author: ryancflam
Author-email: ryancflam@hotmail.com
License: UNKNOWN
Platform: UNKNOWN
Classifier: Programming Language :: Python :: 3
Classifier: Programming Language :: Python :: 3.6
Classifier: License :: OSI Approved :: MIT License
Classifier: Operating System :: OS Independent
Requires-Python: >=3.6
